Workbook

Sheet Vocabulary Lists
A1: Id | B1: StageId | C1: LessonId | D1: Audio ID | E1: Gender | F1: Number | G1: Word | H1: Meaning (English) | I1: Meaning (Italian)
A2: 1 | B2: 1 | C2: 1 | D2: 1-1-1 | E2: Male | F2: Singular | G2: هَٰذَا | H2: This | I2: Questo
A3: 2 | B3: 1 | C3: 1 | D3: 1-1-2 | E3: Male | F3: Singular | G3: ذَٰلِكَ | H3: That | I3: Quello
A4: 3 | B4: 1 | C4: 1 | D4: 1-1-3 | E4: Female | F4: Singular | G4: هَٰذِهِ | H4: This | I4: Questa
A5: 4 | B5: 1 | C5: 1 | D5: 1-1-4 | E5: Female | F5: Singular | G5: تِلۡكَ | H5: That | I5: Quella
A6: 5 | B6: 1 | C6: 1 | D6: 1-1-5 | F6: Plural | G6: هَٰٓؤُلَآء | H6: These | I6: Questi
A7: 6 | B7: 1 | C7: 1 | D7: 1-1-6 | F7: Plural | G7: أُوْلَٰٓئِكَ | H7: Those | I7: Quelli
A8: 7 | B8: 1 | C8: 1 | D8: 1-1-7 | E8: Male | F8: Singular | G8: ٱلَّذِي | H8: who | I8: Il quale / Che
A9: 8 | B9: 1 | C9: 1 | D9: 1-1-8 | E9: Female | F9: Singular | G9: ٱلَّتِي | H9: who | I9: La quale / Che
A10: 9 | B10: 1 | C10: 1 | D10: 1-1-9 | F10: Plural | G10: ٱلَّذِينَ | H10: Those who | I10: Coloro che / I quali
A11: 10 | B11: 1 | C11: 1 | D11: 1-1-10 | F11: Plural | G11: ٱلَّتِي | H11: Those who | I11: Coloro che / Le quali
A12: 11 | B12: 1 | C12: 1 | D12: 1-1-11 | F12: Plural | G12: هَٰذِهِ | H12: These | I12: Questi
A13: 12 | B13: 1 | C13: 1 | D13: 1-1-12 | F13: Plural | G13: تِلۡكَ | H13: Those | I13: Quelli
A14: 13 | B14: 1 | C14: 2 | D14: 1-2-1 | G14: نَعَمۡ | H14: Yes | I14: Sì
A15: 14 | B15: 1 | C15: 2 | D15: 1-2-2 | G15: بَلَي | H15: Yes, indeed | I15: Sì, certo / Bensì
A16: 15 | B16: 1 | C16: 2 | D16: 1-2-3 | G16: كَلَّا | H16: Certainly not | I16: Certo che no / Giammai
A17: 16 | B17: 1 | C17: 2 | D17: 1-2-4 | G17: إِلَّا | H17: Except | I17: Eccetto / Tranne
A18: 17 | B18: 1 | C18: 2 | D18: 1-2-5 | G18: إِنۡ .. إِلَّا | H18: Nothing but | I18: Nient'altro che / Soltanto
A19: 18 | B19: 1 | C19: 2 | D19: 1-2-6 | G19: مَا .. إِلَّا | H19: Nothing but | I19: Nient'altro che / Soltanto
A20: 19 | B20: 1 | C20: 2 | D20: 1-2-7 | G20: أَلَّا | H20: So as not to/ that not | I20: Affinchè non / Per non
A21: 20 | B21: 1 | C21: 2 | D21: 1-2-8 | G21: لَا | H21: Do(es) not | I21: Non
A22: 21 | B22: 1 | C22: 2 | D22: 1-2-9 | G22: مَا | H22: Not (continuous) | I22: Non (continuo)
A23: 22 | B23: 1 | C23: 2 | D23: 1-2-10 | G23: لَنۡ | H23: Will not | I23: Non (futuro)
A24: 23 | B24: 1 | C24: 2 | D24: 1-2-11 | G24: لَمۡ | H24: Did not | I24: Non (passato)
A25: 24 | B25: 1 | C25: 2 | D25: 1-2-12 | E25: Male | F25: Singular | G25: لَيۡسَ | H25: (There is) no | I25: Non è / Non c'è
A26: 25 | B26: 1 | C26: 2 | D26: 1-2-13 | E26: Female | F26: Singular | G26: لَيۡسَت | H26: (There is) no | I26: Non è / Non c'è
A27: 26 | B27: 1 | C27: 2 | D27: 1-2-14 | G27: غَيۡر | H27: Other than | I27: All'infuori di
A28: 27 | B28: 1 | C28: 2 | D28: 1-2-15 | G28: غَيۡر | H28: not | I28: Non
A29: 28 | B29: 1 | C29: 2 | D29: 1-2-16 | G29: مِن دُون | H29: Apart from | I29: A parte / All'infuori di
A30: 29 | B30: 1 | C30: 3 | D30: 1-3-1 | G30: أَ | H30: Yes/ no Questions | I30: Domande Sì / no
A31: 30 | B31: 1 | C31: 3 | D31: 1-3-2 | G31: هَلۡ | H31: Yes/ no Questions | I31: Domande Sì / no
A32: 31 | B32: 1 | C32: 3 | D32: 1-3-3 | G32: مَا | H32: What ...? | I32: Cosa...?
A33: 32 | B33: 1 | C33: 3 | D33: 1-3-4 | G33: مَاذا | H33: What ...? | I33: Che cosa...?
A34: 33 | B34: 1 | C34: 3 | D34: 1-3-5 | G34: لِمَ | H34: Why…? | I34: Perché...?
A35: 34 | B35: 1 | C35: 3 | D35: 1-3-6 | G35: مَنۡ | H35: Who...? | I35: Chi...?
A36: 35 | B36: 1 | C36: 3 | D36: 1-3-7 | G36: مَتَى | H36: When ...? | I36: Quando…?
A37: 36 | B37: 1 | C37: 3 | D37: 1-3-8 | G37: أَيۡنَ | H37: Where...? | I37: Dove…?
A38: 37 | B38: 1 | C38: 3 | D38: 1-3-9 | G38: كَيۡفَ | H38: How...? | I38: Come…?
... A175: 174 | B175: 2 | C175: 2 | D175: 2-2-20 | G175: أَدۡنَى | H175: Nearer/ More likely | I175: Più vicino / Più atto
A176: 175 | B176: 2 | C176: 3 | D176: 2-3-1 | E176: Male | F176: Singular | G176: رَسُول | H176: Messenger | I176: Messaggero
A177: 176 | B177: 2 | C177: 3 | D177: 2-3-2 | F177: Plural | G177: رُسُل | H177: Messengers | I177: Messaggeri
A178: 177 | B178: 2 | C178: 3 | D178: 2-3-3 | F178: Singular | G178: نَبِي | H178: Prophet | I178: Profeta
A179: 178 | B179: 2 | C179: 3 | D179: 2-3-4 | F179: Plural | G179: أَنۢبِيَآء | H179: Prophets | I179: Profeti
A180: 179 | B180: 2 | C180: 3 | D180: 2-3-5 | F180: Plural | G180: نَّبِيُّونَ | H180: Prophets | I180: Profeti
A181: 180 | B181: 2 | C181: 3 | D181: 2-3-6 | F181: Plural | G181: نَّبِيِّـۧنَ | H181: Prophets | I181: Profeti
A182: 181 | B182: 2 | C182: 3 | D182: 2-3-7 | G182: أَمِين | H182: Trustworthy/ Honest | I182: Fidato / Onesto
A183: 182 | B183: 2 | C183: 3 | D183: 2-3-8 | G183: نَذِير | H183: Warner | I183: Ammonitore
A184: 183 | B184: 2 | C184: 3 | D184: 2-3-9 | G184: مُوسَىٰ | H184: Moses | I184: Mosè
A185: 184 | B185: 2 | C185: 3 | D185: 2-3-10 | G185: هَٰرُون | H185: Aaron | I185: Aronne
A186: 185 | B186: 2 | C186: 3 | D186: 2-3-11 | G186: إِبۡرَٰهِـۧم (إِبۡرَٰهِيم) | H186: Abraham | I186: Abramo
A187: 186 | B187: 2 | C187: 3 | D187: 2-3-12 | G187: إِسۡمَٰعِيل | H187: Ishmael | I187: Ismaele
A188: 187 | B188: 2 | C188: 3 | D188: 2-3-13 | G188: نُوح | H188: Noah | I188: Noè
A189: 188 | B189: 2 | C189: 3 | D189: 2-3-14 | G189: يُوسُف | H189: Joseph | I189: Giuseppe
A190: 189 | B190: 2 | C190: 3 | D190: 2-3-15 | G190: لُوط | H190: Lot | I190: Lot
A191: 190 | B191: 2 | C191: 3 | D191: 2-3-16 | G191: عِيسَى ٱبۡنِ مَرۡيَم | H191: Jesus, son of Mary | I191: Gesù figlio di Maria
A192: 191 | B192: 2 | C192: 3 | D192: 2-3-17 | G192: ءَادَم | H192: Adam | I192: Adamo
A193: 192 | B193: 2 | C193: 3 | D193: 2-3-18 | G193: سُلَيۡمَٰن | H193: Solomon | I193: Salomone
... A204: 203 | B204: 2 | C204: 3 | D204: 2-3-29 | G204: هُود (عَاد) | H204: Hud (‘Aad) | I204: Hud ('Ad)
A205: 204 | B205: 2 | C205: 4 | D205: 2-4-1 | F205: Singular | G205: ءَاية | H205: Sign/ verse | I205: Segno / Versetto
A206: 205 | B206: 2 | C206: 4 | D206: 2-4-2 | F206: Plural | G206: ءَايات | H206: Signs/ verses | I206: Segni / Versetti
A207: 206 | B207: 2 | C207: 4 | D207: 2-4-3 | G207: ٱلۡقُرۡءَان | H207: The Quran | I207: Il Corano
A208: 207 | B208: 2 | C208: 4 | D208: 2-4-4 | G208: ٱلۡإِنجِيل | H208: The Gospel | I208: Il Vangelo
A209: 208 | B209: 2 | C209: 4 | D209: 2-4-5 | G209: ٱلتَّوۡرَىٰة | H209: The Torah | I209: La Torah
A210: 209 | B210: 2 | C210: 4 | D210: 2-4-6 | G210: أَنۡعَام | H210: Livestock | I210: Bestiame
A211: 210 | B211: 2 | C211: 4 | D211: 2-4-7 | F211: Singular | G211: جَبَل | H211: Mountain | I211: Montagna
A212: 211 | B212: 2 | C212: 4 | D212: 2-4-8 | F212: Plural | G212: جِبَال | H212: Mountains | I212: Montagne
A213: 212 | B213: 2 | C213: 4 | D213: 2-4-9 | G213: بَـحۡر | H213: Sea/ River | I213: Mare
A214: 213 | B214: 2 | C214: 4 | D214: 2-4-10 | F214: Singular | G214: نَهَر | H214: River | I214: Fiume / Ruscello
A215: 214 | B215: 2 | C215: 4 | D215: 2-4-11 | F215: Plural | G215: أَنۡهَٰر | H215: Rivers | I215: Fiumi / Ruscelli
A216: 215 | B216: 2 | C216: 4 | D216: 2-4-12 | G216: شَمۡس | H216: Sun | I216: Sole
A217: 216 | B217: 2 | C217: 4 | D217: 2-4-13 | G217: قَمَر | H217: Moon | I217: Luna
A218: 217 | B218: 2 | C218: 4 | D218: 2-4-14 | G218: لَيۡل | H218: Night | I218: Notte
A219: 218 | B219: 2 | C219: 4 | D219: 2-4-15 | G219: نَهَار | H219: Daytime | I219: Giorno (Ore di luce)
A220: 219 | B220: 2 | C220: 4 | D220: 2-4-16 | G220: أَرۡض | H220: Earth | I220: Terra
A221: 220 | B221: 2 | C221: 4 | D221: 2-4-17 | G221: سَمَآء | H221: Heaven/ Sky | I221: Cielo
A222: 221 | B222: 2 | C222: 4 | D222: 2-4-18 | G222: سَمَٰوَٰت | H222: Heavens/ Sky | I222: Cieli
A223: 222 | B223: 2 | C223: 4 | D223: 2-4-19 | G223: ءَالَآء | H223: Favors | I223: Favori
A224: 223 | B224: 2 | C224: 4 | D224: 2-4-20 | G224: نِعۡمَة | H224: Favor/ Bounty | I224: Beneficio / Favore
A225: 224 | B225: 2 | C225: 4 | D225: 2-4-21 | G225: فَضۡل | H225: Favor/ Grace | I225: Grazia / Favore
A226: 225 | B226: 2 | C226: 4 | D226: 2-4-22 | G226: مَآء | H226: Water | I226: Acqua
A227: 226 | B227: 2 | C227: 5 | D227: 2-5-1 | G227: دِين | H227: Religion | I227: Religione
A228: 227 | B228: 2 | C228: 5 | D228: 2-5-2 | F228: Singular | G228: أَمۡر | H228: Matter/ Command | I228: Affare / Questione / Ordine / Comando
A229: 228 | B229: 2 | C229: 5 | D229: 2-5-3 | F229: Plural | G229: أُمُور | H229: Matters/ Affairs | I229: Faccende / Questioni
A230: 229 | B230: 2 | C230: 5 | D230: 2-5-4 | G230: صَلَوٰة /صَلَاة | H230: Prayer | I230: Preghiera / Orazione
A231: 230 | B231: 2 | C231: 5 | D231: 2-5-5 | G231: زَّكَوٰة | H231: (Zakah) Charity | I231: (Zakah) Elemosina / Decima
A232: 231 | B232: 2 | C232: 5 | D232: 2-5-6 | G232: حَقّ | H232: Truth/ Right | I232: Verità / Diritto
A233: 232 | B233: 2 | C233: 5 | D233: 2-5-7 | G233: بَٰطِل | H233: Falsehood | I233: Falsità / Menzogna
A234: 233 | B234: 2 | C234: 5 | D234: 2-5-8 | G234: حَمۡد | H234: Praise | I234: Lode
A235: 234 | B235: 2 | C235: 5 | D235: 2-5-9 | G235: حِكۡمَة | H235: Wisdom | I235: Saggezza
A236: 235 | B236: 2 | C236: 5 | D236: 2-5-10 | G236: تَقۡوى | H236: Piety/ Fear of Allah | I236: Pietà / Timore di Allah
A237: 236 | B237: 2 | C237: 5 | D237: 2-5-11 | F237: Singular | G237: شَهِيد | H237: Witness | I237: Testimone
A238: 237 | B238: 2 | C238: 5 | D238: 2-5-12 | F238: Plural | G238: شُهَدَاء | H238: Witnesses | I238: Testimoni
A239: 238 | B239: 2 | C239: 5 | D239: 2-5-13 | F239: Plural | G239: شُهَدَاء | H239: Martyrs | I239: Martiri
A240: 239 | B240: 2 | C240: 5 | D240: 2-5-14 | G240: مُبِين | H240: Clear | I240: Chiaro / Evidente
A241: 240 | B241: 2 | C241: 5 | D241: 2-5-15 | G241: نُور | H241: Light | I241: Luce
A242: 241 | B242: 2 | C242: 5 | D242: 2-5-16 | G242: سَلَٰم | H242: Peace | I242: Pace
A243: 242 | B243: 2 | C243: 5 | D243: 2-5-17 | G243: مُلۡك | H243: Dominion/ Reign | I243: Sovranità
A244: 243 | B244: 2 | C244: 5 | D244: 2-5-18 | G244: سُلۡطَٰن | H244: Warrant/ Proof | I244: Prova / Autorità
A245: 244 | B245: 2 | C245: 5 | D245: 2-5-19 | G245: سُلۡطَٰن | H245: Authority | I245: Autorità
A246: 245 | B246: 2 | C246: 6 | D246: 2-6-1 | F246: Singular | G246: إِلَٰه | H246: god/ deity | I246: divinità / dio
...

Sheet Vocab with Examples
A1: Ayahref | B1: WordID | C1: Word | D1: Meaning & Translation in Italian (Hamza Roberto Piccardo) | E1: Meaning & Translation | F1: Highlight
B2: 1 | C2: هَٰذَا | D2: =VLOOKUP(B2, 'Vocabulary Lists'!A:I, 9, FALSE) -> Questo | E2: This
A3: 2:25 | C3: قَالُواْ هَٰذَا ٱلَّذِي رُزِقۡنَا مِن قَبۡلُۖ | D3: diranno: “(questo) Già ci era stato concesso!” | E3: They will say, “This is what we were provided with before,” | F3: هَٰذَا
A4: 2:26 | C4: مَاذَآ أَرَادَ ٱللَّهُ بِهَٰذَا مَثَلٗاۘ | D4: “Cosa vuol dire Allah con un simile (questo) esempio?” | E4: “What did Allah intend by this example?” | F4: بِهَٰذَا
A5: 30:56 | C5: فَهَٰذَا يَوۡمُ ٱلۡبَعۡثِ | D5: ecco (questo è) il Giorno della Resurrezione | E5: This is the Day of Resurrection | F5: فَهَٰذَا
B6: 2 | C6: ذَٰلِكَ | D6: =VLOOKUP(B6, 'Vocabulary Lists'!A:I, 9, FALSE) -> Quello | E6: That
A7: 2:2 | C7: ذَٰلِكَ ٱلۡكِتَٰبُ لَا رَيۡبَۛ فِيهِۛ | D7: Questo (quello) è il Libro su cui non ci sono dubbi | E7: This (that) is the Book in which there is no doubt | F7: بِذَٰلِكَ
A8: 45:24 | C8: وَمَا لَهُم بِذَٰلِكَ مِنۡ عِلۡمٍۖ إِنۡ هُمۡ إِلَّا يَظُنُّون | D8: Invece (di quello) non possiedono nessuna scienza, non fanno altro che illazioni. | E8: Of that they have no knowledge; they are only assuming. | F8: فَذَٰلِكَ
A9: 74:9 | C9: فَذَٰلِكَ يَوۡمَئِذٖ يَوۡمٌ عَسِيرٌ | D9: quello sarà un Giorno difficile, | E9: That Day will be a difficult day. | F9: فَذَٰلِكَ
B10: 3 | C10: هَٰذِهِ | D10: =VLOOKUP(B10, 'Vocabulary Lists'!A:I, 9, FALSE) -> Questa | E10: This
A11: 7:19 | C11: وَلَا تَقۡرَبَا هَٰذِهِ ٱلشَّجَرَةَ | D11: ma non avvicinatevi a questo albero | E11: but do not approach this tree | F11: هَٰذِهِ
A12: 16:30 | C12: لِّلَّذِينَ أَحۡسَنُواْ فِي هَٰذِهِ ٱلدُّنۡيَا حَسَنَةٞۚ | D12: Coloro che fanno il bene avranno il bene in questa vita | E12: For those who do good in this world, is goodness. | F12: هَٰذِهِ
A13: 26:155 | C13: قَالَ هَٰذِهِۦ نَاقَةٞ لَّهَا شِرۡبٞ | D13: “Questa è una cammella: berrà e voi berrete nei giorni stabiliti." | E13: “This is a she-camel; she has her turn of drinking,” | F13: هَٰذِهِۦ
B14: 4 | C14: تِلۡكَ | D14: =VLOOKUP(B14, 'Vocabulary Lists'!A:I, 9, FALSE) -> Quella | E14: That
A15: 2:134 | C15: تِلۡكَ أُمَّةٞ قَدۡ خَلَتۡۖ | D15: Questa (quella) è gente del passato. | E15: That was a nation that has passed on; | F15: تِلۡكَ
A16: 6:83 | C16: وَتِلۡكَ حُجَّتُنَآ ءَاتَيۡنَٰهَآ إِبۡرَٰهِيمَ عَلَىٰ قَوۡمِهِۦۚ | D16: Questo (quello) è l'argomento che fornimmo ad Abramo contro la sua gente. | E16: That was Our argument which We gave to Abraham against his people. | F16: تِلۡكَ
B17: 5 | C17: هَٰٓؤُلَآء | D17: =VLOOKUP(B17, 'Vocabulary Lists'!A:I, 9, FALSE) -> Questi | E17: These
A18: 4:41 | C18: وَجِئۡنَا بِكَ عَلَىٰ هَٰٓؤُلَآءِ شَهِيدٗا | D18: e ti chiameremo a testimone contro di loro (di questi)? | E18: And We bring you as a witness against these? | F18: هَٰٓؤُلَآءِ
A19: 6:53 | C19: لِّيَقُولُوٓاْ أَهَٰٓؤُلَآءِ مَنَّ ٱللَّهُ عَلَيۡهِم | D19: “Sono questi coloro fra noi che Allah ha favorito?” | E19: “Are these the ones whom Allah has favored from among us?” | F19: أَهَٰٓؤُلَآءِ
B20: 6 | C20: أُوْلَٰٓئِكَ | D20: =VLOOKUP(B20, 'Vocabulary Lists'!A:I, 9, FALSE) -> Quelli | E20: Those
A21: 2:5 | C21: أُوْلَٰٓئِكَ عَلَىٰ هُدٗى مِّن رَّبِّهِمۡۖ وَأُوْلَٰٓئِكَ هُمُ ٱلۡمُفۡلِحُونَ | D21: Quelli seguono la guida del loro Signore; quelli sono coloro che prospereranno. | E21: Those are upon [right] guidance from their Lord, and it is those who are the successful. | F21: فَأُوْلَٰٓئِكَ
A22: 2:160 | C22: فَأُوْلَٰٓئِكَ أَتُوبُ عَلَيۡهِمۡ وَأَنَا ٱلتَّوَّابُ ٱلرَّحِيمُ | D22: da costoro (da quelli) Io accetto il pentimento. Io sono Colui Che accoglie il pentimento, il Misericordioso. | E22: Those—I will accept their repentance. I am the Acceptor of Repentance, the Merciful. | F22: فَأُوْلَٰٓئِكَ
B23: 7 | C23: ٱلَّذِي | D23: =VLOOKUP(B23, 'Vocabulary Lists'!A:I, 9, FALSE) -> Il quale / Che | E23: He who
A24: 2:17 | C24: مَثَلُهُمۡ كَمَثَلِ ٱلَّذِي ٱسۡتَوۡقَدَ نَارٗا | D24: Assomigliano a chi (qualcuno che) accende un fuoco | E24: Their likeness is that of a person who kindled a fire; | F24: ٱلَّذِي
A25: 2:259 | C25: أَوۡ كَٱلَّذِي مَرَّ عَلَىٰ قَرۡيَةٖ | D25: O colui che passando presso una città | E25: Or like him who passed by a town | F25: كَٱلَّذِي
A26: 3:72 | C26: ءَامِنُواْ بِٱلَّذِيٓ أُنزِلَ عَلَى ٱلَّذِينَ ءَامَنُواْ | D26: “All'inizio del giorno credete in quello che è stato fatto scendere su coloro che credono | E26: Believe in that which was revealed to the believers | F26: بِٱلَّذِيٓ
B27: 8 | C27: ٱلَّتِي | D27: =VLOOKUP(B27, 'Vocabulary Lists'!A:I, 9, FALSE) -> La quale / Che | E27: She who
A28: 3:131 | C28: وَٱتَّقُواْ ٱلنَّارَ ٱلَّتِيٓ أُعِدَّتۡ لِلۡكَٰفِرِينَ | D28: E temete il Fuoco che è stato preparato per i miscredenti. | E28: And guard yourselves against the Fire that is prepared for the disbelievers. | F28: ٱلَّتِيٓ
A29: 23:96 | C29: ٱدۡفَعۡ بِٱلَّتِي هِيَ أَحۡسَنُ ٱلسَّيِّئَةَۚ نَحۡنُ أَعۡلَمُ بِمَا يَصِفُونَ | D29: Respingi il male con ciò che è migliore. Ben sappiamo quel che dicono. | E29: Repel evil by what is better. We are aware of what they describe. | F29: بِٱلَّتِي
A30: 16:92 | C30: وَلَا تَكُونُواْ كَٱلَّتِي نَقَضَتۡ غَزۡلَهَا | D30: Non fate come colei che disfaceva il suo filato dopo averlo torto a fatica | E30: And do not be like her who untwisted her spun thread, | F30: كَٱلَّتِي
B31: 9 | C31: ٱلَّذِينَ | D31: =VLOOKUP(B31, 'Vocabulary Lists'!A:I, 9, FALSE) -> Coloro che / I quali | E31: Those who
A32: 1:7 | C32: صِرَٰطَ ٱلَّذِينَ أَنۡعَمۡتَ عَلَيۡهِمۡ | D32: la via di coloro che hai colmato di grazia | E32: The path of those whom You have blessed, | F32: ٱلَّذِينَ
A33: 3:105 | C33: وَلَا تَكُونُواْ كَٱلَّذِينَ تَفَرَّقُواْ | D33: E non siate come coloro che si sono divisi | E33: And do not be like those who became divided | F33: كَٱلَّذِينَ
A34: 6:10 | C34: فَحَاقَ بِٱلَّذِينَ سَخِرُواْ مِنۡهُم | D34: Quello di cui si burlavano, (coloro che si burlavano) oggi li avvolge. | E34: but those who mocked them were enveloped by what they used to ridicule. | F34: بِٱلَّذِينَ
B35: 10 | C35: ٱلَّتِي | D35: =VLOOKUP(B35, 'Vocabulary Lists'!A:I, 9, FALSE) -> Coloro che / Le quali | E35: Those who
A36: 7: 157 | C36: وَيَضَعُ عَنۡهُمۡ إِصۡرَهُمۡ وَٱلۡأَغۡلَٰلَ ٱلَّتِي كَانَتۡ عَلَيۡهِمۡۚ | D36: che li libera del loro fardello e dei legami che li opprimono. | E36: and relieves them of their burden and the shackles which were upon zthem. | F36: ٱلَّتِي
A37: 11: 101 | C37: فَمَآ أَغۡنَتۡ عَنۡهُمۡ ءَالِهَتُهُمُ ٱلَّتِي يَدۡعُونَ مِن دُونِ ٱللَّهِ | D37: Gli dèi che invocavano all'infuori di Allah, non li hanno in nulla protetti | E37: And they were not availed at all by their gods which they invoked other than Allah. | F37: ٱلَّتِي
B38: 11 | C38: هَٰذِهِ | D38: =VLOOKUP(B38, 'Vocabulary Lists'!A:I, 9, FALSE) -> Questi | E38: These
A39: 6: 138 | C39: وَقَالُواْ هَٰذِهِۦٓ أَنۡعَٰمٞ وَحَرۡثٌ حِجۡرٞ لَّا يَطۡعَمُهَآ إِلَّا مَن نَّشَآءُ بِزَعۡمِهِمۡ | D39: E dicono: “Ecco (questi sono) i greggi e le messi consacrate: potranno cibarsene solo quelli che designeremo”. Quali pretese! | E39: «And they say, “These animals and crops are forbidden; no one may eat from them except whom we will,” by their claim. | F39: هَٰذِهِۦٓ
A40: 21: 52 | C40: إِذۡ قَالَ لِأَبِيهِ وَقَوۡمِهِۦ مَا هَٰذِهِ ٱلتَّمَاثِيلُ ٱلَّتِيٓ أَنتُمۡ لَهَا عَٰكِفُونَ | D40: Quando disse a suo padre e alla sua gente: “Cosa sono queste statue in cui credete?”. | E40: «When he said to his father and his people, “What are these statues to which you are devoted?”(52)» | F40: هَٰذِهِ
B41: 12 | C41: تِلۡكَ | D41: =VLOOKUP(B41, 'Vocabulary Lists'!A:I, 9, FALSE) -> Quelli | E41: Those
A42: 2:111 | C42: تِلۡكَ أَمَانِيُّهُمۡۗ | D42: Questo (quello) è quello che vorrebbero! | E42: Those are their wishes. | F42: تِلۡكَ
A43: 4:13 | C43: تِلۡكَ حُدُودُ ٱللَّهِۚ | D43: Questi (quelli) sono i limiti di Allah. | E43: Those are the bounds set by Allah. | F43: تِلۡكَ
B44: 13 | C44: نَعَمۡ | D44: =VLOOKUP(B44, 'Vocabulary Lists'!A:I, 9, FALSE) -> Sì | E44: Yes
A45: 7:44 | C45: فَهَلۡ وَجَدتُّم مَّا وَعَدَ رَبُّكُمۡ حَقّٗاۖ قَالُواْ نَعَمۡ | D45: E voi avete verificato quello che vi era stato promesso?”. “Sì”, diranno. | E45: “Did you find what your Lord promised you to be true?” They will say, “Yes.” | F45: نَعَمۡ
A46: 7:114 | C46: قَالَ نَعَمۡ وَإِنَّكُمۡ لَمِنَ ٱلۡمُقَرَّبِينَ | D46: Disse: “Sì, e inoltre sarete tra i favoriti”. | E46: He said, “Yes, and you will be among my favorites.” | F46: نَعَمۡ
B47: 14 | C47: بَلَي | D47: =VLOOKUP(B47, 'Vocabulary Lists'!A:I, 9, FALSE) -> Sì, certo / Bensì | E47: Yes, indeed
A48: 2:81 | C48: بَلَىٰۚ مَن كَسَبَ سَيِّئَةٗ وَأَحَٰطَتۡ بِهِۦ خَطِيٓـَٔتُهُ | D48: Badate (bensì), chi opera il male ed è circondato dal suo errore | E48: Yes Indeed, whoever commits misdeeds, and becomes besieged by his iniquities— | F48: بَلَىٰۚ
A49: 2:112 | C49: بَلَىٰۚ مَنۡ أَسۡلَمَ وَجۡهَهُۥ لِلَّهِ وَهُوَ مُحۡسِنٞ | D49: Invece (bensì) coloro che sottomettono ad Allah il loro volto e compiono il bene | E49: Indeed, whoever submits his face in Islam to Allah while being a doer of good | F49: بَلَىٰۚ
B50: 15 | C50: كَلَّا | D50: =VLOOKUP(B50, 'Vocabulary Lists'!A:I, 9, FALSE) -> Certo che no / Giammai | E50: Certainly not
A51: 19:79 | C51: كَلَّاۚ سَنَكۡتُبُ مَا يَقُولُ | D51: Certo che no! Annoteremo quello che dice | E51: No indeed! We will write what he says, | F51: كَلَّاۚ
A52: 23:100 | C52: كَلَّآۚ إِنَّهَا كَلِمَةٌ هُوَ قَآئِلُهَاۖ | D52: No! Non è altro che la [vana] parola che [egli] pronuncia | E52: Certainly not! It is just a word he is saying. | F52: كَلَّآۚ
B53: 16 | C53: إِلَّا | D53: =VLOOKUP(B53, 'Vocabulary Lists'!A:I, 9, FALSE) -> Eccetto / Tranne | E53: Except
A54: 3:2 | C54: ٱللَّهُ لَآ إِلَٰهَ إِلَّا هُوَ ٱلۡحَيُّ ٱلۡقَيُّومُۚ | D54: Allah, non c'è dio all'infuori di Lui, il Vivente, l'Assoluto. | E54: Allah - there is no deity except Him, the Ever-Living, the Sustainer of [all] existence. | F54: إِلَّا
A55: 2:255 | C55: مَن ذَا ٱلَّذِي يَشۡفَعُ عِندَهُۥٓ إِلَّا بِإِذۡنِهِ | D55: Chi può intercedere presso di Lui senza (eccetto che con) il Suo permesso? | E55: Who is he that can intercede with Him except with His permission? | F55: إِلَّا
B56: 17 | C56: إِنۡ .. إِلَّا | D56: =VLOOKUP(B56, 'Vocabulary Lists'!A:I, 9, FALSE) -> Nient'altro che / Soltanto | E56: Nothing but
A57: 4:62 | C57: ثُمَّ جَآءُوكَ يَحۡلِفُونَ بِٱللَّهِ إِنۡ أَرَدۡنَآ إِلَّآ إِحۡسَٰنٗا وَتَوۡفِيقًا | D57: Perseguivamo (nient'altro che) il bene e la concordia! | E57: We intended nothing but good conduct and accommodation. | F57: إِنۡ .. إِلَّا
A58: 34:43 | C58: إِنۡ هَٰذَآ إِلَّا سِحۡرٞ مُّبِينٞ | D58: “Questa non è (altro) che evidente magia!”. | E58: “This is nothing but plain magic.” | F58: إِنۡ .. إِلَّا
B59: 18 | C59: مَا .. إِلَّا | D59: =VLOOKUP(B59, 'Vocabulary Lists'!A:I, 9, FALSE) -> Nient'altro che / Soltanto | E59: Nothing but
A60: 5:117 | C60: مَا قُلۡتُ لَهُمۡ إِلَّا مَآ أَمَرۡتَنِي بِهِۦ | D60: Ho detto loro solo quello che Tu mi avevi ordinato di dire | E60: I said not to them except what You commanded me | F60: مَا .. إِلَّا
A61: 23:24 | C61: فَقَالَ ٱلۡمَلَؤُاْ ٱلَّذِينَ كَفَرُواْ مِن قَوۡمِهِۦ مَا هَٰذَآ إِلَّا بَشَرٞ مِّثۡلُكُمۡ | D61: Allora i notabili della sua gente, che erano miscredenti, dissero: “Costui non è (altro) che un uomo come voi! | E61: But the notables of his people, who disbelieved, said, “This is nothing but a human like you,” | F61: مَا .. إِلَّا
B62: 19 | C62: أَلَّا | D62: =VLOOKUP(B62, 'Vocabulary Lists'!A:I, 9, FALSE) -> Affinchè non / Per non | E62: So as not to/ that not
A63: 12:40 | C63: إِنِ ٱلۡحُكۡمُ إِلَّا لِلَّهِ أَمَرَ أَلَّا تَعۡبُدُوٓاْ إِلَّآ إِيَّاهُۚ | D63: Egli vi ha ordinato di non adorare altri che Lui. | E63: He has commanded that you worship none but Him. | F63: أَلَّا
A64: 14:12 | C64: وَمَا لَنَآ أَلَّا نَتَوَكَّلَ عَلَى ٱللَّهِ | D64: E come potremmo non confidare in Allah | E64: And why should we not rely upon Allah | F64: أَلَّا
B65: 20 | C65: لَا | D65: =VLOOKUP(B65, 'Vocabulary Lists'!A:I, 9, FALSE) -> Non | E65: Do(es) not
A66: 88:11 | C66: لَّا تَسۡمَعُ فِيهَا لَٰغِيَةٗ | D66: in cui non s'odono discorsi vani. | E66: Wherein they will hear no unsuitable speech. | F66: لَا
A67: 88:7 | C67: لَّا يُسۡمِنُ وَلَا يُغۡنِي مِن جُوعٖ | D67: che non nutre e non placa la fame. | E67: That neither nourishes, nor satisfies hunger. | F67: لَا
B68: 21 | C68: مَا | D68: =VLOOKUP(B68, 'Vocabulary Lists'!A:I, 9, FALSE) -> Non (continuo) | E68: Not (continuous)
A69: 2:9 | C69: يُخَٰدِعُونَ ٱللَّهَ وَٱلَّذِينَ ءَامَنُواْ وَمَا يَخۡدَعُونَ إِلَّآ أَنفُسَهُمۡ | D69: Cercano di ingannare Allah e coloro che credono, ma non ingannano che loro stessi | E69: They seek to deceive Allah and those who believe, but they deceive none but themselves, | F69: مَا
A70: 2:102 | C70: وَمَا كَفَرَ سُلَيۡمَٰنُ وَلَٰكِنَّ ٱلشَّيَٰطِينَ كَفَرُواْ | D70: Non era stato Salomone il miscredente, ma i dèmoni | E70: Solomon disbelieved not, but the Satans disbelieved, | F70: مَا
B71: 22 | C71: لَنۡ | D71: =VLOOKUP(B71, 'Vocabulary Lists'!A:I, 9, FALSE) -> Non (futuro) | E71: Will not
A72: 12:66 | C72: قَالَ لَنۡ أُرۡسِلَهُۥ مَعَكُمۡ حَتَّىٰ تُؤۡتُونِ مَوۡثِقٗا مِّنَ ٱللَّهِ | D72: Disse [Giacobbe]: “Non lo manderò con voi, finché non giurerete su Allah" | E72: He said, “I will not send him with you, unless you give me a pledge before Allah” | F72: لَنۡ
A73: 12:80 | C73: فَلَنۡ أَبۡرَحَ ٱلۡأَرۡضَ حَتَّىٰ يَأۡذَنَ لِيٓ أَبِيٓ | D73: Non lascerò questo territorio, senza che mio padre me ne dia il permesso | E73: I will not leave this land until my father permits me, | F73: فَلَنۡ
B74: 23 | C74: لَمۡ | D74: =VLOOKUP(B74, 'Vocabulary Lists'!A:I, 9, FALSE) -> Non (passato) | E74: Did not
A75: 2:151 | C75: وَيُعَلِّمُكُمُ ٱلۡكِتَٰبَ وَٱلۡحِكۡمَةَ وَيُعَلِّمُكُم مَّا لَمۡ تَكُونُواْ تَعۡلَمُونَ | D75: e vi insegni il Libro e la saggezza e vi insegni quello che non sapevate. | E75: and teach you the Book and the wisdom, and teaching you that which you did not know; | F75: لَمۡ
A76: 2:247 | C76: وَنَحۡنُ أَحَقُّ بِٱلۡمُلۡكِ مِنۡهُ وَلَمۡ يُؤۡتَ سَعَةٗ مِّنَ ٱلۡمَالِۚ | D76: Noi abbiamo più diritto di lui a regnare, e a lui non sono state concesse ricchezze!” | E76: when we are more worthy of authority than he, and he was not given plenty of wealth?” | F76: لَمۡ
B77: 24 | C77: لَيۡسَ | D77: =VLOOKUP(B77, 'Vocabulary Lists'!A:I, 9, FALSE) -> Non è / Non c'è | E77: (There is) no
A78: 88:6 | C78: لَّيۡسَ لَهُمۡ طَعَامٌ إِلَّا مِن ضَرِيعٖ | D78: Per essi non ci sarà altro cibo che il darî, | E78: For them, there will be no food except from a poisonous, thorny plant | F78: لَّيۡسَ
A79: 24:29 | C79: لَّيۡسَ عَلَيۡكُمۡ جُنَاحٌ أَن تَدۡخُلُواْ بُيُوتًا غَيۡرَ مَسۡكُونَةٖ | D79: Non ci sarà colpa da parte vostra, se entrerete in case diverse dalle abitazioni, nelle quali si trovi qualcosa a voi utile | E79: There is no blame on you for entering uninhabited houses, | F79: لَّيۡسَ
B80: 25 | C80: لَيۡسَت | D80: =VLOOKUP(B80, 'Vocabulary Lists'!A:I, 9, FALSE) -> Non è / Non c'è | E80: (There is) no
A81: 2:113 | C81: وَقَالَتِ ٱلۡيَهُودُ لَيۡسَتِ ٱلنَّصَٰرَىٰ عَلَىٰ شَيۡءٖ | D81: Gli ebrei dicono: “I nazareni si basano sul nulla”; | E81: The Jews say, “The Christians are not based on anything;” | F81: لَيۡسَتِ
B82: 26 | C82: غَيۡر | D82: =VLOOKUP(B82, 'Vocabulary Lists'!A:I, 9, FALSE) -> All'infuori di | E82: Other than
A83: 28:71 | C83: مَنۡ إِلَٰهٌ غَيۡرُ ٱللَّهِ يَأۡتِيكُم بِضِيَآءٍۚ | D83: quale altra divinità all'infuori di Allah potrebbe darvi la luce? | E83: what deity other than Allah could bring you light? | F83: غَيۡرُ
B84: 27 | C84: غَيۡر | D84: =VLOOKUP(B84, 'Vocabulary Lists'!A:I, 9, FALSE) -> Non | E84: not
A85: 1:7 | C85: صِرَٰطَ ٱلَّذِينَ أَنۡعَمۡتَ عَلَيۡهِمۡ غَيۡرِ ٱلۡمَغۡضُوبِ عَلَيۡهِمۡ وَلَا ٱلضَّآلِّينَ | D85: la via di coloro che hai colmato di grazia, non di coloro che [sono incorsi] nella [Tua] ira, né degli sviati. | E85: The path of those upon whom You have bestowed favor, not of those who have evoked [Your] anger or of those who are astray. | F85: غَيۡرِ
B86: 28 | C86: مِن دُون | D86: =VLOOKUP(B86, 'Vocabulary Lists'!A:I, 9, FALSE) -> A parte / All'infuori di | E86: Apart from
A87: 29:22 | C87: وَمَا لَكُم مِّن دُونِ ٱللَّهِ مِن وَلِيّٖ وَلَا نَصِيرٖ | D87: all'infuori di Allah, non c'è per voi né padrone, né difensore. | E87: and apart from Allah you have no protector or helper? | F87: مِّن دُونِ
A88: 29:25 | C88: وَقَالَ إِنَّمَا ٱتَّخَذۡتُم مِّن دُونِ ٱللَّهِ أَوۡثَٰنٗا | D88: Disse: “Invero, non avete adottato gli idoli, all'infuori di Allah | E88: And [Abraham] said, “You have only taken, apart from Allah, idols” | F88: مِّن دُونِ
B89: 29 | C89: أَ | D89: =VLOOKUP(B89, 'Vocabulary Lists'!A:I, 9, FALSE) -> Domande Sì / no | E89: Yes/ no Questions
A90: 5:53 | C90: أَهَٰٓؤُلَآءِ ٱلَّذِينَ أَقۡسَمُواْ بِٱللَّهِ جَهۡدَ أَيۡمَٰنِهِمۡ إِنَّهُمۡ لَمَعَكُمۡۚ | D90: “Questi sono coloro che giuravano [in nome] di Allah, con giuramento solenne, che erano con voi?” | E90: Are these the ones who swore by Allah most earnest oaths that they were with you? | F90: أَهَٰٓؤُلَآءِ
A91: 21:36 | C91: أَهَٰذَا ٱلَّذِي يَذۡكُرُ ءَالِهَتَكُمۡ | D91: “Cosa? È costui che dice male dei vostri dèi?” | E91: Is this the one who insults your gods? | F91: أَهَٰذَا
A92: 12:39 | C92: ءَأَرۡبَابٞ مُّتَفَرِّقُونَ خَيۡرٌ أَمِ ٱللَّهُ ٱلۡوَٰحِدُ ٱلۡقَهَّارُ | D92: Una miriade di signori sono forse meglio di Allah, l'Unico, Colui Che prevale? | E92: Are separate lords better or Allah, the One, the Prevailing? | F92: ءَأَرۡبَابٞ
B93: 30 | C93: هَلۡ | D93: =VLOOKUP(B93, 'Vocabulary Lists'!A:I, 9, FALSE) -> Domande Sì / no | E93: Yes/ no Questions
A94: 3:154 | C94: يَقُولُونَ هَل لَّنَا مِنَ ٱلۡأَمۡرِ مِن شَيۡءٖۗ | D94: Dicevano: “(Cosa) abbiamo guadagnato [qualcosa] in questa impresa?” | E94: saying, "Is there anything for us [to have done] in this matter?" | F94: هَل
A95: 5:91 | C95: وَيَصُدَّكُمۡ عَن ذِكۡرِ ٱللَّهِ وَعَنِ ٱلصَّلَوٰةِۖ فَهَلۡ أَنتُم مُّنتَهُونَ | D95: e allontanarvi dal Ricordo di Allah e dall'orazione. Ve ne asterrete? | E95: and to prevent you from the remembrance of Allah, and from prayer. Will you not desist? | F95: فَهَلۡ
B96: 31 | C96: مَا | D96: =VLOOKUP(B96, 'Vocabulary Lists'!A:I, 9, FALSE) -> Cosa...? | E96: What (question word)
A97: 7:12 | C97: قَالَ مَا مَنَعَكَ أَلَّا تَسۡجُدَ إِذۡ أَمَرۡتُكَۖ | D97: Disse [Allah]: “Cosa mai ti impedisce di prosternarti, nonostante il Mio ordine?” | E97: He said, “What prevented you from prostrating when I have commanded you?” | F97: مَا
B98: 32 | C98: مَاذا | D98: =VLOOKUP(B98, 'Vocabulary Lists'!A:I, 9, FALSE) -> Che cosa...? | E98: What ...?
A99: 26:35 | C99: يُرِيدُ أَن يُخۡرِجَكُم مِّنۡ أَرۡضِكُم بِسِحۡرِهِۦ فَمَاذَا تَأۡمُرُونَ | D99: vuole cacciarvi dalla vostra terra con la sua magia. Ebbene, che cosa deliberate?”. | E99: “He wants to evict you from your land, so what do you recommend?” | F99: فَمَاذَا
A100: 27:28 | C100: فَأَلۡقِهۡ إِلَيۡهِمۡ ثُمَّ تَوَلَّ عَنۡهُمۡ فَٱنظُرۡ مَاذَا يَرۡجِعُونَ | D100: e falla cadere su di loro; mettiti poi in disparte e aspetta ciò che le sarà risposto”. | E100: and deliver it to them. Then leave them and see what [answer] they will return. | F100: مَاذَا
...

Sheet Stages
A1: 1 | B1: PART I | C1: From 0% to 50%
A2: 2 | B2: PART II | C2: From 50% to 65%
A3: 3 | B3: PART III | C3: From 65% to 85%

Sheet Lessons
A2: 1 | B2: 1 | C2: Demonstrative Pronouns
A3: 2 | B3: 1 | C3: Negations & Exceptions
A4: 3 | B4: 1 | C4: Question Words
A5: 4 | B5: 1 | C5: Prepositions I
A6: 5 | B6: 1 | C6: Prepositions II
A7: 6 | B7: 1 | C7: Connectors
A8: 7 | B8: 1 | C8: Miscellaneous
A9: 8 | B9: 1 | C9: Types of ما
A10: 1 | B10: 2 | C10: Allāh’s names & attributes
A11: 2 | B11: 2 | C11: Attributes/ adjectives
A12: 3 | B12: 2 | C12: Prophets and Messengers
A13: 4 | B13: 2 | C13: Allāh’s signs & blessings
... A40: 19 | B40: 3 | C40: Irregular Verbs 5
